thonny_ozobot-0.3.dist-info/DESCRIPTION.rst
thonny_ozobot-0.3.dist-info/METADATA
thonny_ozobot-0.3.dist-info/RECORD
thonny_ozobot-0.3.dist-info/WHEEL
thonny_ozobot-0.3.dist-info/metadata.json
thonny_ozobot-0.3.dist-info/top_level.txt
thonnycontrib/ozobot/__init__.py
